.flake8
ChangeLog
LICENSE
MANIFEST.in
Makefile
README.md
pyproject.toml
setup.cfg
tox.ini
doc/Makefile
doc/conf.py
doc/config.rst
doc/core.rst
doc/core_api.rst
doc/example_app.rst
doc/example_plugin.rst
doc/fs.rst
doc/index.rst
doc/logs.rst
doc/mainloop.rst
doc/promise.rst
examples/core_plugins.py
l10n/ca.po
l10n/de.po
l10n/es.po
l10n/fr.po
l10n/messages.pot
l10n/oc.po
l10n/sv.po
l10n/uk.po
l10n/zh_Hans.po
src/openpaperwork_core/__init__.py
src/openpaperwork_core/_version.py
src/openpaperwork_core/app.py
src/openpaperwork_core/archives.py
src/openpaperwork_core/censor.py
src/openpaperwork_core/data_versioning.py
src/openpaperwork_core/deps.py
src/openpaperwork_core/flatpak.py
src/openpaperwork_core/frozen.py
src/openpaperwork_core/http.py
src/openpaperwork_core/interactive.py
src/openpaperwork_core/promise.py
src/openpaperwork_core/sqlite.py
src/openpaperwork_core/uncaught_exception.py
src/openpaperwork_core/urls.py
src/openpaperwork_core.egg-info/PKG-INFO
src/openpaperwork_core.egg-info/SOURCES.txt
src/openpaperwork_core.egg-info/dependency_links.txt
src/openpaperwork_core.egg-info/requires.txt
src/openpaperwork_core.egg-info/top_level.txt
src/openpaperwork_core/beacon/__init__.py
src/openpaperwork_core/beacon/stats.py
src/openpaperwork_core/beacon/sysinfo.py
src/openpaperwork_core/bug_report/__init__.py
src/openpaperwork_core/bug_report/censor.py
src/openpaperwork_core/cmd/__init__.py
src/openpaperwork_core/cmd/chkdeps.py
src/openpaperwork_core/cmd/config.py
src/openpaperwork_core/cmd/ping.py
src/openpaperwork_core/cmd/plugins.py
src/openpaperwork_core/cmd/util.py
src/openpaperwork_core/config/__init__.py
src/openpaperwork_core/config/automatic_plugin_reset.py
src/openpaperwork_core/config/fake.py
src/openpaperwork_core/config/backend/__init__.py
src/openpaperwork_core/config/backend/configparser.py
src/openpaperwork_core/debug/__init__.py
src/openpaperwork_core/debug/objgraph.py
src/openpaperwork_core/debug/pympler.py
src/openpaperwork_core/display/__init__.py
src/openpaperwork_core/display/print.py
src/openpaperwork_core/external_apps/__init__.py
src/openpaperwork_core/external_apps/dbus.py
src/openpaperwork_core/external_apps/windows.py
src/openpaperwork_core/external_apps/xdg.py
