Metadata-Version: 2.1
Name: openpaperwork-core
Version: 2.2.4
Summary: OpenPaperwork's core
Author-email: Jerome Flesch <jflesch@openpaper.work>
License: GPL-3.0-or-later
License-File: LICENSE
Requires-Dist: certifi
Requires-Dist: distro
Provides-Extra: dev
Requires-Dist: pytest; extra == "dev"
Provides-Extra: lint
Requires-Dist: flake8; extra == "lint"
